{"kind": "youtube#videoListResponse", "etag": "\"j6xRRd8dTPVVptg711_CSPADRfg/AoMyVlklt7o7cVCysjoldGhEVW8\"", "pageInfo": {"totalResults": 1, "resultsPerPage": 1}, "items": [{"kind": "youtube#video", "etag": "\"j6xRRd8dTPVVptg711_CSPADRfg/Srfa2knELWqBTj6HL2yTroHKyUQ\"", "id": "0mKmYxuMirE", "snippet": {"publishedAt": "2011-11-09T20:24:32.000Z", "channelId": "UC4a-Gbdw7vOaccHmFo40b9g", "title": "Congruent and Similar Triangles", "description": "u07_l1_t3_we2 Congruent and Similar Triangles\nContent provided by TheNROCproject.org - (c) Monterey Institute for Technology and Education", "thumbnails": {"default": {"url": "https://i.ytimg.com/vi/0mKmYxuMirE/default.jpg", "width": 120, "height": 90}, "medium": {"url": "https://i.ytimg.com/vi/0mKmYxuMirE/mqdefault.jpg", "width": 320, "height": 180}, "high": {"url": "https://i.ytimg.com/vi/0mKmYxuMirE/hqdefault.jpg", "width": 480, "height": 360}, "standard": {"url": "https://i.ytimg.com/vi/0mKmYxuMirE/sddefault.jpg", "width": 640, "height": 480}, "maxres": {"url": "https://i.ytimg.com/vi/0mKmYxuMirE/maxresdefault.jpg", "width": 1280, "height": 720}}, "channelTitle": "Khan Academy", "categoryId": "27", "liveBroadcastContent": "none", "localized": {"title": "Congruent and Similar Triangles", "description": "u07_l1_t3_we2 Congruent and Similar Triangles\nContent provided by TheNROCproject.org - (c) Monterey Institute for Technology and Education"}, "defaultAudioLanguage": "en"}}]}
