{"kind": "youtube#videoListResponse", "etag": "\"j6xRRd8dTPVVptg711_CSPADRfg/R2m1Syyjidi0CdfR0avPDdhT1oI\"", "pageInfo": {"totalResults": 1, "resultsPerPage": 1}, "items": [{"kind": "youtube#video", "etag": "\"j6xRRd8dTPVVptg711_CSPADRfg/Z_xVvynRE8p44KS8fKWotfba_WU\"", "id": "12Q3Mrh03Gk", "snippet": {"publishedAt": "2017-04-20T19:42:20.000Z", "channelId": "UCs4aHmggTfFrpkPcWSaBN9g", "title": "How to Break Cryptography | Infinite Series", "description": "Viewers like you help make PBS (Thank you 😃) . Support your local PBS Member Station here: https://to.pbs.org/donateinfi\n\nOnly 4 steps stand between you and the secrets hidden behind RSA cryptography. Find out how to crack the world’s most commonly used form of encryption.\n\nTweet at us! @pbsinfinite\nFacebook: facebook.com/pbsinfinite series\nEmail us! pbsinfiniteseries [at] gmail [dot] com\n\nPrevious Episode:\nCan We Combine pi & e into a Rational Number?\nhttps://www.youtube.com/watch?v=bG7cCXqcJag&t=25s\n\nLinks to other resources:\n\nShor's paper: https://arxiv.org/abs/quant-ph/9508027v2\n\nLecture on Shor's Algorithm: https://arxiv.org/pdf/quant-ph/0010034.pdf\n\nBlog on Shor's algorithm: http://www.scottaaronson.com/blog/?p=208\n\nVideo on RSA cryptography: https://www.youtube.com/watch?v=wXB-V_Keiu8\n\nAnother video on RSA cryptography: https://www.youtube.com/watch?v=4zahvcJ9glg\n\nEuler's Big Idea: https://en.wikipedia.org/wiki/Euler%27s_theorem  (I can find a non-wiki article, but I don't actually use this in the video. It's just where to learn more about the relevant math Euler did.)\n\nWritten and Hosted by Kelsey Houston-Edwards\nProduced by Rusty Ward\nGraphics by Ray Lux\nMade by Kornhaber Brown (www.kornhaberbrown.com)\n\nChallenge Winner - Reddles37\nhttps://www.youtube.com/watch?v=bG7cCXqcJag&lc=z135cnmgxlbwch1ds233sbzgaojkivaz004\n\nComments answered by Kelsey:\n\nJoel David Hamkins\nhttps://www.youtube.com/watch?v=bG7cCXqcJag&lc=z13zdpcwyk2ofhugh04cdh4agsr2whmbsmk0k\n\nPCreeper394\nhttps://www.youtube.com/watch?v=bG7cCXqcJag&lc=z135w324kw21j1qi104cdzvrpoixslmq1jw", "thumbnails": {"default": {"url": "https://i.ytimg.com/vi/12Q3Mrh03Gk/default.jpg", "width": 120, "height": 90}, "medium": {"url": "https://i.ytimg.com/vi/12Q3Mrh03Gk/mqdefault.jpg", "width": 320, "height": 180}, "high": {"url": "https://i.ytimg.com/vi/12Q3Mrh03Gk/hqdefault.jpg", "width": 480, "height": 360}, "standard": {"url": "https://i.ytimg.com/vi/12Q3Mrh03Gk/sddefault.jpg", "width": 640, "height": 480}, "maxres": {"url": "https://i.ytimg.com/vi/12Q3Mrh03Gk/maxresdefault.jpg", "width": 1280, "height": 720}}, "channelTitle": "PBS Infinite Series", "tags": ["math", "mathematics", "education", "science", "cryptography", "encryption", "security", "prime numbers", "primes", "factoring", "factor", "hack", "break", "crack", "shor''s", "algorithim"], "categoryId": "27", "liveBroadcastContent": "none", "defaultLanguage": "en", "localized": {"title": "How to Break Cryptography | Infinite Series", "description": "Viewers like you help make PBS (Thank you 😃) . Support your local PBS Member Station here: https://to.pbs.org/donateinfi\n\nOnly 4 steps stand between you and the secrets hidden behind RSA cryptography. Find out how to crack the world’s most commonly used form of encryption.\n\nTweet at us! @pbsinfinite\nFacebook: facebook.com/pbsinfinite series\nEmail us! pbsinfiniteseries [at] gmail [dot] com\n\nPrevious Episode:\nCan We Combine pi & e into a Rational Number?\nhttps://www.youtube.com/watch?v=bG7cCXqcJag&t=25s\n\nLinks to other resources:\n\nShor's paper: https://arxiv.org/abs/quant-ph/9508027v2\n\nLecture on Shor's Algorithm: https://arxiv.org/pdf/quant-ph/0010034.pdf\n\nBlog on Shor's algorithm: http://www.scottaaronson.com/blog/?p=208\n\nVideo on RSA cryptography: https://www.youtube.com/watch?v=wXB-V_Keiu8\n\nAnother video on RSA cryptography: https://www.youtube.com/watch?v=4zahvcJ9glg\n\nEuler's Big Idea: https://en.wikipedia.org/wiki/Euler%27s_theorem  (I can find a non-wiki article, but I don't actually use this in the video. It's just where to learn more about the relevant math Euler did.)\n\nWritten and Hosted by Kelsey Houston-Edwards\nProduced by Rusty Ward\nGraphics by Ray Lux\nMade by Kornhaber Brown (www.kornhaberbrown.com)\n\nChallenge Winner - Reddles37\nhttps://www.youtube.com/watch?v=bG7cCXqcJag&lc=z135cnmgxlbwch1ds233sbzgaojkivaz004\n\nComments answered by Kelsey:\n\nJoel David Hamkins\nhttps://www.youtube.com/watch?v=bG7cCXqcJag&lc=z13zdpcwyk2ofhugh04cdh4agsr2whmbsmk0k\n\nPCreeper394\nhttps://www.youtube.com/watch?v=bG7cCXqcJag&lc=z135w324kw21j1qi104cdzvrpoixslmq1jw"}, "defaultAudioLanguage": "en"}}]}
