{"kind": "youtube#videoListResponse", "etag": "\"j6xRRd8dTPVVptg711_CSPADRfg/FJSbNME6KzcN1OYAY6QoX2fKC9k\"", "pageInfo": {"totalResults": 1, "resultsPerPage": 1}, "items": [{"kind": "youtube#video", "etag": "\"j6xRRd8dTPVVptg711_CSPADRfg/7RQy1ai7vcpWNbvin8Wgi_S1j3Q\"", "id": "1EDCyM41BWQ", "snippet": {"publishedAt": "2014-05-31T00:59:17.000Z", "channelId": "UCq0EGvLTyy-LLT1oUSO_0FQ", "title": "Multiplying Mixed Numerals", "description": "", "thumbnails": {"default": {"url": "https://i.ytimg.com/vi/1EDCyM41BWQ/default.jpg", "width": 120, "height": 90}, "medium": {"url": "https://i.ytimg.com/vi/1EDCyM41BWQ/mqdefault.jpg", "width": 320, "height": 180}, "high": {"url": "https://i.ytimg.com/vi/1EDCyM41BWQ/hqdefault.jpg", "width": 480, "height": 360}, "standard": {"url": "https://i.ytimg.com/vi/1EDCyM41BWQ/sddefault.jpg", "width": 640, "height": 480}, "maxres": {"url": "https://i.ytimg.com/vi/1EDCyM41BWQ/maxresdefault.jpg", "width": 1280, "height": 720}}, "channelTitle": "Eddie Woo", "categoryId": "27", "liveBroadcastContent": "none", "localized": {"title": "Multiplying Mixed Numerals", "description": ""}}}]}
