{"kind": "youtube#videoListResponse", "etag": "\"j6xRRd8dTPVVptg711_CSPADRfg/g8xZusMGtFkTUlhoRc6LFtddT9k\"", "pageInfo": {"totalResults": 1, "resultsPerPage": 1}, "items": [{"kind": "youtube#video", "etag": "\"j6xRRd8dTPVVptg711_CSPADRfg/QfHkqZ5pWsJbG-KlitZ97OHnHjc\"", "id": "3xwDryouw6o", "snippet": {"publishedAt": "2012-04-17T07:10:19.000Z", "channelId": "UCBuMwlP7kHkNxdPAqtFSJTw", "title": "Math Antics - Fractions Are Division", "description": "Learn More at mathantics.com\nVisit http://www.mathantics.com for more Free math videos and additional subscription based content!", "thumbnails": {"default": {"url": "https://i.ytimg.com/vi/3xwDryouw6o/default.jpg", "width": 120, "height": 90}, "medium": {"url": "https://i.ytimg.com/vi/3xwDryouw6o/mqdefault.jpg", "width": 320, "height": 180}, "high": {"url": "https://i.ytimg.com/vi/3xwDryouw6o/hqdefault.jpg", "width": 480, "height": 360}, "standard": {"url": "https://i.ytimg.com/vi/3xwDryouw6o/sddefault.jpg", "width": 640, "height": 480}, "maxres": {"url": "https://i.ytimg.com/vi/3xwDryouw6o/maxresdefault.jpg", "width": 1280, "height": 720}}, "channelTitle": "mathantics", "tags": ["Math", "fraction", "fractions", "educational", "Math Antics", "arithmetic", "multi-digit", "addition", "subtraction", "multiplication", "division", "numerator", "denominator"], "categoryId": "27", "liveBroadcastContent": "none", "localized": {"title": "Math Antics - Fractions Are Division", "description": "Learn More at mathantics.com\nVisit http://www.mathantics.com for more Free math videos and additional subscription based content!"}, "defaultAudioLanguage": "en"}}]}
