{"kind": "youtube#videoListResponse", "etag": "\"j6xRRd8dTPVVptg711_CSPADRfg/shyLK-1LsnHJpdr8PbvgNgI_dLk\"", "pageInfo": {"totalResults": 1, "resultsPerPage": 1}, "items": [{"kind": "youtube#video", "etag": "\"j6xRRd8dTPVVptg711_CSPADRfg/3XsFMY1N6QwovOhmCeq5LnOvSeM\"", "id": "9ubEYX7raoM", "snippet": {"publishedAt": "2015-01-05T02:52:46.000Z", "channelId": "UCfG0OGu8IR9KqgZiDQOHIfg", "title": "Chord and Tangent Properties", "description": "Special properties of chords and tangents. Several conjectures which will be very useful when solving circle problems.", "thumbnails": {"default": {"url": "https://i.ytimg.com/vi/9ubEYX7raoM/default.jpg", "width": 120, "height": 90}, "medium": {"url": "https://i.ytimg.com/vi/9ubEYX7raoM/mqdefault.jpg", "width": 320, "height": 180}, "high": {"url": "https://i.ytimg.com/vi/9ubEYX7raoM/hqdefault.jpg", "width": 480, "height": 360}, "standard": {"url": "https://i.ytimg.com/vi/9ubEYX7raoM/sddefault.jpg", "width": 640, "height": 480}}, "channelTitle": "Kealing Geometry", "categoryId": "27", "liveBroadcastContent": "none", "localized": {"title": "Chord and Tangent Properties", "description": "Special properties of chords and tangents. Several conjectures which will be very useful when solving circle problems."}}}]}
