{"kind": "youtube#videoListResponse", "etag": "\"j6xRRd8dTPVVptg711_CSPADRfg/zU3pXcUwGkvHlLGWqiGyd0cIM3E\"", "pageInfo": {"totalResults": 1, "resultsPerPage": 1}, "items": [{"kind": "youtube#video", "etag": "\"j6xRRd8dTPVVptg711_CSPADRfg/9whshyKqcEjaLw8lOREW9flgfZk\"", "id": "cyW5z-M2yzw", "snippet": {"publishedAt": "2015-10-04T02:14:13.000Z", "channelId": "UCYO_jab_esuFRV4b17AJtAw", "title": "Music And Measure Theory", "description": "A connection between a classical puzzle about rational numbers and what makes music harmonious.", "thumbnails": {"default": {"url": "https://i.ytimg.com/vi/cyW5z-M2yzw/default.jpg", "width": 120, "height": 90}, "medium": {"url": "https://i.ytimg.com/vi/cyW5z-M2yzw/mqdefault.jpg", "width": 320, "height": 180}, "high": {"url": "https://i.ytimg.com/vi/cyW5z-M2yzw/hqdefault.jpg", "width": 480, "height": 360}, "standard": {"url": "https://i.ytimg.com/vi/cyW5z-M2yzw/sddefault.jpg", "width": 640, "height": 480}, "maxres": {"url": "https://i.ytimg.com/vi/cyW5z-M2yzw/maxresdefault.jpg", "width": 1280, "height": 720}}, "channelTitle": "3Blue1Brown", "tags": ["measure theory", "real analysis", "3 blue 1 brown", "Mathematics", "3 brown 1 blue", "three brown one blue", "3b1b", "3brown1blue", "three blue one brown", "music theory"], "categoryId": "27", "liveBroadcastContent": "none", "defaultLanguage": "en", "localized": {"title": "Music And Measure Theory", "description": "A connection between a classical puzzle about rational numbers and what makes music harmonious."}, "defaultAudioLanguage": "en"}}]}
