{"kind": "youtube#videoListResponse", "etag": "\"j6xRRd8dTPVVptg711_CSPADRfg/4twsekIjK1mBX3YIiK9r6k1fnHQ\"", "pageInfo": {"totalResults": 1, "resultsPerPage": 1}, "items": [{"kind": "youtube#video", "etag": "\"j6xRRd8dTPVVptg711_CSPADRfg/pQMQ_SbB3ntsagmbGSbhU8_NNGg\"", "id": "eEQMNczG5K0", "snippet": {"publishedAt": "2017-04-23T23:30:41.000Z", "channelId": "UCib_J32VI8rQI_LCFXn1XAA", "title": "Lesson 5.4 of Exploding Dots", "description": "This is the 12th lesson in the story of Exploding Dots for Global Math Week 2017 (www.theglobalmathproject.org).", "thumbnails": {"default": {"url": "https://i.ytimg.com/vi/eEQMNczG5K0/default.jpg", "width": 120, "height": 90}, "medium": {"url": "https://i.ytimg.com/vi/eEQMNczG5K0/mqdefault.jpg", "width": 320, "height": 180}, "high": {"url": "https://i.ytimg.com/vi/eEQMNczG5K0/hqdefault.jpg", "width": 480, "height": 360}, "standard": {"url": "https://i.ytimg.com/vi/eEQMNczG5K0/sddefault.jpg", "width": 640, "height": 480}, "maxres": {"url": "https://i.ytimg.com/vi/eEQMNczG5K0/maxresdefault.jpg", "width": 1280, "height": 720}}, "channelTitle": "James Tanton", "tags": ["Exploding Dots", "Mathematics", "Global Math Project"], "categoryId": "1", "liveBroadcastContent": "none", "defaultLanguage": "en", "localized": {"title": "Lesson 5.4 of Exploding Dots", "description": "This is the 12th lesson in the story of Exploding Dots for Global Math Week 2017 (www.theglobalmathproject.org)."}, "defaultAudioLanguage": "en-US"}}]}
