{"kind": "youtube#videoListResponse", "etag": "\"j6xRRd8dTPVVptg711_CSPADRfg/hK-GkuioJJZnhGuR_5LKM3L_JeM\"", "pageInfo": {"totalResults": 1, "resultsPerPage": 1}, "items": [{"kind": "youtube#video", "etag": "\"j6xRRd8dTPVVptg711_CSPADRfg/mqWwYl4wx19u-NDBKfDifIo38g0\"", "id": "GX-YdOykky4", "snippet": {"publishedAt": "2010-09-08T22:05:00.000Z", "channelId": "UCFe6jenM1Bc54qtBsIJGRZQ", "title": "Graphing a Rational Function that has an Oblique/Slant Asymptote and  a Vertical Asymptote", "description": "Thanks to all of you who support me on Patreon. You da real mvps!   $1 per month helps!! :)  https://www.patreon.com/patrickjmt !! Graphing a Rational Function that has an Oblique/Slant Asymptote and a vertical asymptote.  One example!", "thumbnails": {"default": {"url": "https://i.ytimg.com/vi/GX-YdOykky4/default.jpg", "width": 120, "height": 90}, "medium": {"url": "https://i.ytimg.com/vi/GX-YdOykky4/mqdefault.jpg", "width": 320, "height": 180}, "high": {"url": "https://i.ytimg.com/vi/GX-YdOykky4/hqdefault.jpg", "width": 480, "height": 360}, "standard": {"url": "https://i.ytimg.com/vi/GX-YdOykky4/sddefault.jpg", "width": 640, "height": 480}, "maxres": {"url": "https://i.ytimg.com/vi/GX-YdOykky4/maxresdefault.jpg", "width": 1280, "height": 720}}, "channelTitle": "patrickJMT", "tags": ["math", "algebra", "oblique", "slant", "horizontal", "vertical", "asymptote", "long", "division", "synthetic", "rational", "function", "medina", "washington"], "categoryId": "27", "liveBroadcastContent": "none", "localized": {"title": "Graphing a Rational Function that has an Oblique/Slant Asymptote and  a Vertical Asymptote", "description": "Thanks to all of you who support me on Patreon. You da real mvps!   $1 per month helps!! :)  https://www.patreon.com/patrickjmt !! Graphing a Rational Function that has an Oblique/Slant Asymptote and a vertical asymptote.  One example!"}}}]}
