{"kind": "youtube#videoListResponse", "etag": "\"j6xRRd8dTPVVptg711_CSPADRfg/Svopq4zP8Dd3RFQqCumgRwjv478\"", "pageInfo": {"totalResults": 1, "resultsPerPage": 1}, "items": [{"kind": "youtube#video", "etag": "\"j6xRRd8dTPVVptg711_CSPADRfg/2KOqKWUXgd9Bboo5Ld3TUCMQx9I\"", "id": "HKQbhpIwjrU", "snippet": {"publishedAt": "2012-02-13T19:47:24.000Z", "channelId": "UCQv3dpUXUWvDFQarHrS5P9A", "title": "Graphing the Cotangent Function", "description": "Learn how to graph a cotangent function. To graph a cotangent function, we first determine the period (the distance/time for a complete oscillation), the phase shift (the horizontal shift from the parent function), the vertical shift (the vertical shift from the parent function) and the asymptotes (the two vertical lines which the graph does not touch). After we have obtained these features, we plot the points on the graph and graph accordingly.\n\nSubscribe: https://www.youtube.com/user/mrbrianmclogan?sub_confirmation=1\nWebsite: http://www.freemathvideos.com\nLearn from Udemy: https://www.udemy.com/user/brianmclogan2/\n\nFollow me on \nFacebook: https://www.facebook.com/freemathvideos/\nTwitter https://twitter.com/mrbrianmclogan\n#graphtrig\n#trigonometry #graphtrigfunctions", "thumbnails": {"default": {"url": "https://i.ytimg.com/vi/HKQbhpIwjrU/default.jpg", "width": 120, "height": 90}, "medium": {"url": "https://i.ytimg.com/vi/HKQbhpIwjrU/mqdefault.jpg", "width": 320, "height": 180}, "high": {"url": "https://i.ytimg.com/vi/HKQbhpIwjrU/hqdefault.jpg", "width": 480, "height": 360}, "standard": {"url": "https://i.ytimg.com/vi/HKQbhpIwjrU/sddefault.jpg", "width": 640, "height": 480}, "maxres": {"url": "https://i.ytimg.com/vi/HKQbhpIwjrU/maxresdefault.jpg", "width": 1280, "height": 720}}, "channelTitle": "Brian McLogan", "tags": ["how to graph the cotangent function", "how to graph cotangent", "how to graph", "how to", "cotangent", "cotangent function", "sine equation", "equation", "function", "graph", "graphing", "translation", "transformation", "math help", "shift", "period", "altitude", "x-scale", "change", "plot", "y=3cot (πx/2)", "graph cotangent function", "graph cotangent function online", "कोटेशन फंक्शन", "how to graph tangent and cotangent functions", "sketching the graph of a tangent and cotangent function", "periods", "horizontal translation", "how", "learn math"], "categoryId": "27", "liveBroadcastContent": "none", "defaultLanguage": "en", "localized": {"title": "Graphing the Cotangent Function", "description": "Learn how to graph a cotangent function. To graph a cotangent function, we first determine the period (the distance/time for a complete oscillation), the phase shift (the horizontal shift from the parent function), the vertical shift (the vertical shift from the parent function) and the asymptotes (the two vertical lines which the graph does not touch). After we have obtained these features, we plot the points on the graph and graph accordingly.\n\nSubscribe: https://www.youtube.com/user/mrbrianmclogan?sub_confirmation=1\nWebsite: http://www.freemathvideos.com\nLearn from Udemy: https://www.udemy.com/user/brianmclogan2/\n\nFollow me on \nFacebook: https://www.facebook.com/freemathvideos/\nTwitter https://twitter.com/mrbrianmclogan\n#graphtrig\n#trigonometry #graphtrigfunctions"}, "defaultAudioLanguage": "en-US"}}]}
