{"kind": "youtube#videoListResponse", "etag": "\"j6xRRd8dTPVVptg711_CSPADRfg/0p3iC8mKqRGgvUi23NUGShKfVFY\"", "pageInfo": {"totalResults": 1, "resultsPerPage": 1}, "items": [{"kind": "youtube#video", "etag": "\"j6xRRd8dTPVVptg711_CSPADRfg/x8WPuxawpfL0tImAPi-XIjNlZkM\"", "id": "kvLjpQ0XGao", "snippet": {"publishedAt": "2011-11-30T04:11:35.000Z", "channelId": "UCb7w5aTnt7YeXBcVCY0mgFw", "title": "Fast Multiplication of any number - using vedic math", "description": "This maths trick for fast multiplication allows you multiply any two numbers quickly, using vedic math. This method is a great alternative either for those who need that extra bit of help with math, or people who like to expand their knowledge.\r\nThis trick is especially useful in multiplying large numbers, with less mess and confusion than standard long multiplication. To support free math by tecmath onPatreon (thankyou): https://www.patreon.com/tecmath To donate to the tecmath channel:  https://paypal.me/tecmath?locale.x=en_AU", "thumbnails": {"default": {"url": "https://i.ytimg.com/vi/kvLjpQ0XGao/default.jpg", "width": 120, "height": 90}, "medium": {"url": "https://i.ytimg.com/vi/kvLjpQ0XGao/mqdefault.jpg", "width": 320, "height": 180}, "high": {"url": "https://i.ytimg.com/vi/kvLjpQ0XGao/hqdefault.jpg", "width": 480, "height": 360}, "standard": {"url": "https://i.ytimg.com/vi/kvLjpQ0XGao/sddefault.jpg", "width": 640, "height": 480}}, "channelTitle": "tecmath", "tags": ["multiply any number fast", "multiplication shortcut", "shortcuts", "Multiplication", "Maths", "tricks", "vedic", "math", "homeschool", "home", "school", "Homeschooling"], "categoryId": "27", "liveBroadcastContent": "none", "localized": {"title": "Fast Multiplication of any number - using vedic math", "description": "This maths trick for fast multiplication allows you multiply any two numbers quickly, using vedic math. This method is a great alternative either for those who need that extra bit of help with math, or people who like to expand their knowledge.\r\nThis trick is especially useful in multiplying large numbers, with less mess and confusion than standard long multiplication. To support free math by tecmath onPatreon (thankyou): https://www.patreon.com/tecmath To donate to the tecmath channel:  https://paypal.me/tecmath?locale.x=en_AU"}}}]}
