{"kind": "youtube#videoListResponse", "etag": "\"j6xRRd8dTPVVptg711_CSPADRfg/WyQgVPSYutKHuoov6VODm4RkHro\"", "pageInfo": {"totalResults": 1, "resultsPerPage": 1}, "items": [{"kind": "youtube#video", "etag": "\"j6xRRd8dTPVVptg711_CSPADRfg/vw49RTamj3vYJQGY4ZX33dDSVvE\"", "id": "MFytqBe7VDE", "snippet": {"publishedAt": "2010-04-27T18:40:40.000Z", "channelId": "UCoboTJrMiYw4bKr6cMMy4-A", "title": "Why is tangent called \"tangent\" in trigonometry? (TANTON Mathematics)", "description": "And why is secant called \"secant\" and cosine called co - sine? Why these names? In this video I explain the connection between the tangent of an angle and a tangent line. Ditto for the secant of an angle and a secant line. \r\n\r\nBTW: Did you know that \"sine\" means \"harbour\" or \"cove\"?", "thumbnails": {"default": {"url": "https://i.ytimg.com/vi/MFytqBe7VDE/default.jpg", "width": 120, "height": 90}, "medium": {"url": "https://i.ytimg.com/vi/MFytqBe7VDE/mqdefault.jpg", "width": 320, "height": 180}, "high": {"url": "https://i.ytimg.com/vi/MFytqBe7VDE/hqdefault.jpg", "width": 480, "height": 360}}, "channelTitle": "DrJamesTanton", "tags": ["WhyTangent"], "categoryId": "27", "liveBroadcastContent": "none", "localized": {"title": "Why is tangent called \"tangent\" in trigonometry? (TANTON Mathematics)", "description": "And why is secant called \"secant\" and cosine called co - sine? Why these names? In this video I explain the connection between the tangent of an angle and a tangent line. Ditto for the secant of an angle and a secant line. \r\n\r\nBTW: Did you know that \"sine\" means \"harbour\" or \"cove\"?"}}}]}
