{"kind": "youtube#videoListResponse", "etag": "\"j6xRRd8dTPVVptg711_CSPADRfg/LIW26q1-tDtIJ3h-K-N1PMkKck4\"", "pageInfo": {"totalResults": 1, "resultsPerPage": 1}, "items": [{"kind": "youtube#video", "etag": "\"j6xRRd8dTPVVptg711_CSPADRfg/5WZ3qp1tCXmpdb0gJbAQwL7O-As\"", "id": "nBdWxsm6x5M", "snippet": {"publishedAt": "2014-04-29T23:49:40.000Z", "channelId": "UCq0EGvLTyy-LLT1oUSO_0FQ", "title": "Introduction to Fractions", "description": "", "thumbnails": {"default": {"url": "https://i.ytimg.com/vi/nBdWxsm6x5M/default.jpg", "width": 120, "height": 90}, "medium": {"url": "https://i.ytimg.com/vi/nBdWxsm6x5M/mqdefault.jpg", "width": 320, "height": 180}, "high": {"url": "https://i.ytimg.com/vi/nBdWxsm6x5M/hqdefault.jpg", "width": 480, "height": 360}, "standard": {"url": "https://i.ytimg.com/vi/nBdWxsm6x5M/sddefault.jpg", "width": 640, "height": 480}, "maxres": {"url": "https://i.ytimg.com/vi/nBdWxsm6x5M/maxresdefault.jpg", "width": 1280, "height": 720}}, "channelTitle": "Eddie Woo", "categoryId": "27", "liveBroadcastContent": "none", "localized": {"title": "Introduction to Fractions", "description": ""}}}]}
