{"kind": "youtube#videoListResponse", "etag": "\"j6xRRd8dTPVVptg711_CSPADRfg/Hgp4Rd85sFG3OVZy1shXXLLKp1c\"", "pageInfo": {"totalResults": 1, "resultsPerPage": 1}, "items": [{"kind": "youtube#video", "etag": "\"j6xRRd8dTPVVptg711_CSPADRfg/YvGD5rYoGMZeGb436BftmqgTkpw\"", "id": "O4ndIDcDSGc", "snippet": {"publishedAt": "2017-05-31T13:00:25.000Z", "channelId": "UCoxcjq-8xIDTYp3uz647V5A", "title": "Gödel's Incompleteness Theorem - Numberphile", "description": "Marcus du Sautoy discusses Gödel's Incompleteness Theorem\nMore links & stuff in full description below ↓↓↓\n\nExtra Footage Part One: https://youtu.be/mccoBBf0VDM\nExtra Footage Part Two: https://youtu.be/7DtzChPqUAw\n\nProfessor du Sautoy is Simonyi Professor for the Public Understanding of Science and a Professor of Mathematics at the University of Oxford.\n\nProfessor du Sautoy's book as mentioned...\nIn the US it is called The Great Unknown - http://amzn.to/2sfkWpb\nIn the UK it is called What We Cannot Know - http://amzn.to/2r5yztp\nMore of his books: http://amzn.to/2ryEk4r\n\nDiscuss this one on Brady's subreddit: https://redd.it/6eet91\n\nNumberphile is supported by the Mathematical Sciences Research Institute (MSRI): http://bit.ly/MSRINumberphile\n\nWe are also supported by Science Sandbox, a Simons Foundation initiative dedicated to engaging everyone with the process of science.\n\nNUMBERPHILE\nWebsite: http://www.numberphile.com/\nNumberphile on Facebook: http://www.facebook.com/numberphile\nNumberphile tweets: https://twitter.com/numberphile\nSubscribe: http://bit.ly/Numberphile_Sub\n\nVideos by Brady Haran\nAnimation in this video by Pete McPartlan\n\nPatreon: http://www.patreon.com/numberphile\n\nBrady's videos subreddit: http://www.reddit.com/r/BradyHaran/\n\nBrady's latest videos across all channels: http://www.bradyharanblog.com/\n\nSign up for (occasional) emails: http://eepurl.com/YdjL9", "thumbnails": {"default": {"url": "https://i.ytimg.com/vi/O4ndIDcDSGc/default.jpg", "width": 120, "height": 90}, "medium": {"url": "https://i.ytimg.com/vi/O4ndIDcDSGc/mqdefault.jpg", "width": 320, "height": 180}, "high": {"url": "https://i.ytimg.com/vi/O4ndIDcDSGc/hqdefault.jpg", "width": 480, "height": 360}, "standard": {"url": "https://i.ytimg.com/vi/O4ndIDcDSGc/sddefault.jpg", "width": 640, "height": 480}, "maxres": {"url": "https://i.ytimg.com/vi/O4ndIDcDSGc/maxresdefault.jpg", "width": 1280, "height": 720}}, "channelTitle": "Numberphile", "tags": ["numberphile", "Gödel's Incompleteness Theorem", "kurt godel", "Marcus du Sautoy"], "categoryId": "28", "liveBroadcastContent": "none", "defaultLanguage": "en", "localized": {"title": "Gödel's Incompleteness Theorem - Numberphile", "description": "Marcus du Sautoy discusses Gödel's Incompleteness Theorem\nMore links & stuff in full description below ↓↓↓\n\nExtra Footage Part One: https://youtu.be/mccoBBf0VDM\nExtra Footage Part Two: https://youtu.be/7DtzChPqUAw\n\nProfessor du Sautoy is Simonyi Professor for the Public Understanding of Science and a Professor of Mathematics at the University of Oxford.\n\nProfessor du Sautoy's book as mentioned...\nIn the US it is called The Great Unknown - http://amzn.to/2sfkWpb\nIn the UK it is called What We Cannot Know - http://amzn.to/2r5yztp\nMore of his books: http://amzn.to/2ryEk4r\n\nDiscuss this one on Brady's subreddit: https://redd.it/6eet91\n\nNumberphile is supported by the Mathematical Sciences Research Institute (MSRI): http://bit.ly/MSRINumberphile\n\nWe are also supported by Science Sandbox, a Simons Foundation initiative dedicated to engaging everyone with the process of science.\n\nNUMBERPHILE\nWebsite: http://www.numberphile.com/\nNumberphile on Facebook: http://www.facebook.com/numberphile\nNumberphile tweets: https://twitter.com/numberphile\nSubscribe: http://bit.ly/Numberphile_Sub\n\nVideos by Brady Haran\nAnimation in this video by Pete McPartlan\n\nPatreon: http://www.patreon.com/numberphile\n\nBrady's videos subreddit: http://www.reddit.com/r/BradyHaran/\n\nBrady's latest videos across all channels: http://www.bradyharanblog.com/\n\nSign up for (occasional) emails: http://eepurl.com/YdjL9"}, "defaultAudioLanguage": "en"}}]}
