{"kind": "youtube#videoListResponse", "etag": "\"j6xRRd8dTPVVptg711_CSPADRfg/6q-3Fx3ti1Xwl87jIiAHKx3huPc\"", "pageInfo": {"totalResults": 1, "resultsPerPage": 1}, "items": [{"kind": "youtube#video", "etag": "\"j6xRRd8dTPVVptg711_CSPADRfg/3aDqIVewnXr8TFGqueyaFsKkP0w\"", "id": "qAs50nzzrP4", "snippet": {"publishedAt": "2011-11-10T22:41:06.000Z", "channelId": "UC4a-Gbdw7vOaccHmFo40b9g", "title": "Area of a Trapezoid", "description": "u07_l2_t2_we2 Area of a Trapezoid", "thumbnails": {"default": {"url": "https://i.ytimg.com/vi/qAs50nzzrP4/default.jpg", "width": 120, "height": 90}, "medium": {"url": "https://i.ytimg.com/vi/qAs50nzzrP4/mqdefault.jpg", "width": 320, "height": 180}, "high": {"url": "https://i.ytimg.com/vi/qAs50nzzrP4/hqdefault.jpg", "width": 480, "height": 360}, "standard": {"url": "https://i.ytimg.com/vi/qAs50nzzrP4/sddefault.jpg", "width": 640, "height": 480}, "maxres": {"url": "https://i.ytimg.com/vi/qAs50nzzrP4/maxresdefault.jpg", "width": 1280, "height": 720}}, "channelTitle": "Khan Academy", "tags": ["u07_l2_t2_we2", "Area", "of", "Trapezoid"], "categoryId": "27", "liveBroadcastContent": "none", "localized": {"title": "Area of a Trapezoid", "description": "u07_l2_t2_we2 Area of a Trapezoid"}, "defaultAudioLanguage": "en"}}]}
