{"kind": "youtube#videoListResponse", "etag": "\"j6xRRd8dTPVVptg711_CSPADRfg/YhyHe3CWCdJHIgh95k3YIfpLAfI\"", "pageInfo": {"totalResults": 1, "resultsPerPage": 1}, "items": [{"kind": "youtube#video", "etag": "\"j6xRRd8dTPVVptg711_CSPADRfg/jYPgCH9K151W4Hlz54_LDllc7vM\"", "id": "RAdTpC51nSE", "snippet": {"publishedAt": "2012-01-29T12:16:03.000Z", "channelId": "UCiV741np0dU4N4h9pb1gngQ", "title": "Radians, Arc Length & Sector Area tutorial", "description": "An introduction to the measure of radians and two commonly used radian formulas for the arc length and the sector area of a circle\r\n\r\nhttps://sites.google.com/site/bsbibstandardlevelmaths/home/circular-functions", "thumbnails": {"default": {"url": "https://i.ytimg.com/vi/RAdTpC51nSE/default.jpg", "width": 120, "height": 90}, "medium": {"url": "https://i.ytimg.com/vi/RAdTpC51nSE/mqdefault.jpg", "width": 320, "height": 180}, "high": {"url": "https://i.ytimg.com/vi/RAdTpC51nSE/hqdefault.jpg", "width": 480, "height": 360}, "standard": {"url": "https://i.ytimg.com/vi/RAdTpC51nSE/sddefault.jpg", "width": 640, "height": 480}}, "channelTitle": "BSBmaths", "tags": ["Radians", "arc length", "sector area", "circles"], "categoryId": "27", "liveBroadcastContent": "none", "localized": {"title": "Radians, Arc Length & Sector Area tutorial", "description": "An introduction to the measure of radians and two commonly used radian formulas for the arc length and the sector area of a circle\r\n\r\nhttps://sites.google.com/site/bsbibstandardlevelmaths/home/circular-functions"}}}]}
