{"kind": "youtube#videoListResponse", "etag": "\"j6xRRd8dTPVVptg711_CSPADRfg/o1wy1vuYO0Pnuqpkpw_L5Q9eeUQ\"", "pageInfo": {"totalResults": 1, "resultsPerPage": 1}, "items": [{"kind": "youtube#video", "etag": "\"j6xRRd8dTPVVptg711_CSPADRfg/n-AhVMNkT1ln8VIXd5E8bGZEVNs\"", "id": "ua1K3Eo2PQc", "snippet": {"publishedAt": "2016-04-06T14:42:09.000Z", "channelId": "UCoxcjq-8xIDTYp3uz647V5A", "title": "The Heart of Fermat's Last Theorem - Numberphile", "description": "Modularity... Simon Pampena gets to the heart of proving Fermat's Last Theorem.\nMore links & stuff in full description below ↓↓↓\n\nAudible: www.audible.com/numberphile\nMore Numberphile videos on Fermat: http://bit.ly/fermat_videos\n\nSimon Pampena is Australia's Numeracy Ambassador --- https://twitter.com/mathemaniac\n \nSupport us on Patreon: http://www.patreon.com/numberphile\n\nNUMBERPHILE\nWebsite: http://www.numberphile.com/\nNumberphile on Facebook: http://www.facebook.com/numberphile\nNumberphile tweets: https://twitter.com/numberphile\nSubscribe: http://bit.ly/Numberphile_Sub\n\nNumberphile is supported by the Mathematical Sciences Research Institute (MSRI): http://bit.ly/MSRINumberphile\n\nVideos by Brady Haran\n\nBrady's videos subreddit: http://www.reddit.com/r/BradyHaran/\n\nBrady's latest videos across all channels: http://www.bradyharanblog.com/\n\nSign up for (occasional) emails: http://eepurl.com/YdjL9\n\nNumberphile T-Shirts: https://teespring.com/stores/numberphile\nOther merchandise: https://store.dftba.com/collections/numberphile", "thumbnails": {"default": {"url": "https://i.ytimg.com/vi/ua1K3Eo2PQc/default.jpg", "width": 120, "height": 90}, "medium": {"url": "https://i.ytimg.com/vi/ua1K3Eo2PQc/mqdefault.jpg", "width": 320, "height": 180}, "high": {"url": "https://i.ytimg.com/vi/ua1K3Eo2PQc/hqdefault.jpg", "width": 480, "height": 360}, "standard": {"url": "https://i.ytimg.com/vi/ua1K3Eo2PQc/sddefault.jpg", "width": 640, "height": 480}, "maxres": {"url": "https://i.ytimg.com/vi/ua1K3Eo2PQc/maxresdefault.jpg", "width": 1280, "height": 720}}, "channelTitle": "Numberphile", "tags": ["numberphile", "fermat's last theorem", "andrew wiles"], "categoryId": "28", "liveBroadcastContent": "none", "localized": {"title": "The Heart of Fermat's Last Theorem - Numberphile", "description": "Modularity... Simon Pampena gets to the heart of proving Fermat's Last Theorem.\nMore links & stuff in full description below ↓↓↓\n\nAudible: www.audible.com/numberphile\nMore Numberphile videos on Fermat: http://bit.ly/fermat_videos\n\nSimon Pampena is Australia's Numeracy Ambassador --- https://twitter.com/mathemaniac\n \nSupport us on Patreon: http://www.patreon.com/numberphile\n\nNUMBERPHILE\nWebsite: http://www.numberphile.com/\nNumberphile on Facebook: http://www.facebook.com/numberphile\nNumberphile tweets: https://twitter.com/numberphile\nSubscribe: http://bit.ly/Numberphile_Sub\n\nNumberphile is supported by the Mathematical Sciences Research Institute (MSRI): http://bit.ly/MSRINumberphile\n\nVideos by Brady Haran\n\nBrady's videos subreddit: http://www.reddit.com/r/BradyHaran/\n\nBrady's latest videos across all channels: http://www.bradyharanblog.com/\n\nSign up for (occasional) emails: http://eepurl.com/YdjL9\n\nNumberphile T-Shirts: https://teespring.com/stores/numberphile\nOther merchandise: https://store.dftba.com/collections/numberphile"}, "defaultAudioLanguage": "en"}}]}
