{"kind": "youtube#videoListResponse", "etag": "\"j6xRRd8dTPVVptg711_CSPADRfg/GHOW1PvfyMFRrUYvc8pNg4i70Us\"", "pageInfo": {"totalResults": 1, "resultsPerPage": 1}, "items": [{"kind": "youtube#video", "etag": "\"j6xRRd8dTPVVptg711_CSPADRfg/FIFlTz6azdt-0ciDscHYm13fx9U\"", "id": "uRkfAgQZAhY", "snippet": {"publishedAt": "2008-05-24T02:11:42.000Z", "channelId": "UC28MYq5TxXKT4qDYg6aMQiA", "title": "Algebra - FOIL Multiplying Binomials", "description": "In inside look into the classroom as we delve into the world of multiplying two binomials together, using the classic \"FOIL\" method. YAY MATH!\r\nVisit yaymath.org\r\nVideos copyright (c) Yay Math", "thumbnails": {"default": {"url": "https://i.ytimg.com/vi/uRkfAgQZAhY/default.jpg", "width": 120, "height": 90}, "medium": {"url": "https://i.ytimg.com/vi/uRkfAgQZAhY/mqdefault.jpg", "width": 320, "height": 180}, "high": {"url": "https://i.ytimg.com/vi/uRkfAgQZAhY/hqdefault.jpg", "width": 480, "height": 360}}, "channelTitle": "yaymath", "tags": ["calculus", "college algebra", "solving equations", "square root property", "algebra", "x squared", "pre-calculus", "differences of squares", "factoring", "factoring trinomials", "quadratic functions", "geometry", "high school math", "GRE", "yaymath", "ACT math", "factoring perfect squares", "algebra 2", "solving quadratic equations", "Quantitative", "factoring binomials", "math", "SAT math", "FOIL"], "categoryId": "22", "liveBroadcastContent": "none", "localized": {"title": "Algebra - FOIL Multiplying Binomials", "description": "In inside look into the classroom as we delve into the world of multiplying two binomials together, using the classic \"FOIL\" method. YAY MATH!\r\nVisit yaymath.org\r\nVideos copyright (c) Yay Math"}}}]}
