{"kind": "youtube#videoListResponse", "etag": "\"j6xRRd8dTPVVptg711_CSPADRfg/BM6oUfiOR1geng2Lp1lcZL1pogE\"", "pageInfo": {"totalResults": 1, "resultsPerPage": 1}, "items": [{"kind": "youtube#video", "etag": "\"j6xRRd8dTPVVptg711_CSPADRfg/uiTatOLumJj2FXacsBXPKx5DHBQ\"", "id": "x8-3OlB3G0M", "snippet": {"publishedAt": "2010-10-20T12:07:04.000Z", "channelId": "UCoboTJrMiYw4bKr6cMMy4-A", "title": "A Harmonic Series Paradox (TANTON Mathematics)", "description": "Here's a cute, but disturbing, geometric interpretation of two famous series in mathematics: the harmonic series (which sums to an infinite value) and the Basel series (which sums to a finite value). Put the two together and ... WHOA!", "thumbnails": {"default": {"url": "https://i.ytimg.com/vi/x8-3OlB3G0M/default.jpg", "width": 120, "height": 90}, "medium": {"url": "https://i.ytimg.com/vi/x8-3OlB3G0M/mqdefault.jpg", "width": 320, "height": 180}, "high": {"url": "https://i.ytimg.com/vi/x8-3OlB3G0M/hqdefault.jpg", "width": 480, "height": 360}}, "channelTitle": "DrJamesTanton", "tags": ["HarmonicParadox"], "categoryId": "27", "liveBroadcastContent": "none", "localized": {"title": "A Harmonic Series Paradox (TANTON Mathematics)", "description": "Here's a cute, but disturbing, geometric interpretation of two famous series in mathematics: the harmonic series (which sums to an infinite value) and the Basel series (which sums to a finite value). Put the two together and ... WHOA!"}}}]}
